cindergrace_common/__init__.py
cindergrace_common/backup.py
cindergrace_common/branding.py
cindergrace_common/cli.py
cindergrace_common/config.py
cindergrace_common/i18n.py
cindergrace_common/logging_setup.py
cindergrace_common/openrouter.py
cindergrace_common/secrets.py
cindergrace_common/security.py
cindergrace_common/state.py
cindergrace_common/ui/__init__.py
cindergrace_common/ui/gradio.py
cindergrace_common/utils/__init__.py
cindergrace_common/utils/datetime.py
cindergrace_common/utils/paths.py
cindergrace_common/utils/retry.py
cindergrace_common-0.5.1.dist-info/licenses/LICENSE
cindergrace_common-0.5.1.dist-info/METADATA
cindergrace_common-0.5.1.dist-info/WHEEL
cindergrace_common-0.5.1.dist-info/top_level.txt
cindergrace_common-0.5.1.dist-info/RECORD
