Metadata-Version: 2.4
Name: cindergrace-common
Version: 0.5.1
Summary: Shared utilities for Cindergrace applications
Author-email: Cindergrace <dev@cindergrace.com>
License-Expression: MIT
Project-URL: Homepage, https://github.com/goettemar/cindergrace_common
Project-URL: Repository, https://github.com/goettemar/cindergrace_common
Classifier: Development Status :: 4 - Beta
Classifier: Intended Audience :: Developers
Classifier: Programming Language :: Python :: 3
Classifier: Programming Language :: Python :: 3.10
Classifier: Programming Language :: Python :: 3.11
Classifier: Programming Language :: Python :: 3.12
Requires-Python: >=3.10
License-File: LICENSE
Requires-Dist: pyyaml>=6.0
Provides-Extra: gradio
Requires-Dist: gradio>=4.0.0; extra == "gradio"
Provides-Extra: secrets
Requires-Dist: keyring>=24.0.0; extra == "secrets"
Provides-Extra: openrouter
Requires-Dist: httpx>=0.27.0; extra == "openrouter"
Provides-Extra: dev
Requires-Dist: pytest>=7.0.0; extra == "dev"
Requires-Dist: pytest-cov>=4.0.0; extra == "dev"
Requires-Dist: keyring>=24.0.0; extra == "dev"
Requires-Dist: httpx>=0.27.0; extra == "dev"
Dynamic: license-file
